README.md
setup.cfg
setup.py
simple_pp/__init__.py
simple_pp/__main__.py
simple_pp/aio_headers.py
simple_pp/errors.py
simple_pp/extract_ip_port.py
simple_pp/get_args_simple_pp.py
simple_pp/get_new_loop.py
simple_pp/get_proxies.py
simple_pp/httpx_get.py
simple_pp/limited_as_completed.py
simple_pp/make_url.py
simple_pp/need_to_wrap.py
simple_pp/providers.py
simple_pp/simple_pp.py
simple_pp/timeme.py
simple_pp/utils.py
simple_pp/jhao/__init__.py
simple_pp/jhao/ProxyGetter/CheckProxy.py
simple_pp/jhao/ProxyGetter/__init__.py
simple_pp/jhao/ProxyGetter/getFreeProxy.py
simple_pp/jhao/Util/LogHandler.py
simple_pp/jhao/Util/WebRequest.py
simple_pp/jhao/Util/__init__.py
simple_pp/jhao/Util/utilClass.py
simple_pp/jhao/Util/utilFunction.py
simple_proxy_pool.egg-info/PKG-INFO
simple_proxy_pool.egg-info/SOURCES.txt
simple_proxy_pool.egg-info/dependency_links.txt
simple_proxy_pool.egg-info/requires.txt
simple_proxy_pool.egg-info/top_level.txt
tests/__init__.py
tests/test_limited_as_completed.py
tests/test_need_to_wrap.py
tests/test_setup.py
tests/test_simple_pp.py