Metadata-Version: 2.1
Name: simple-proxy-pool
Version: 0.1.1
Summary: simple proxy pool + proxy validation
Home-page: http://github.com/ffreemt/simple-proxy-pool
Author: mikeee
License: MIT License
Download-URL: https://github.com/ffreemt/simepl-proxy-pool/archive/v_011.tar.gz
Keywords: machine translation,free,scraping
Platform: UNKNOWN
Classifier: Development Status :: 3 - Alpha
Classifier: Intended Audience :: Developers
Classifier: Programming Language :: Python :: 3
Classifier: Programming Language :: Python :: 3.6
Classifier: License :: OSI Approved :: MIT License
